threepanewindows/__init__.py
threepanewindows/_version.py
threepanewindows/cli.py
threepanewindows/custom_scrollbar.py
threepanewindows/dockable.py
threepanewindows/enhanced_dockable.py
threepanewindows/examples.py
threepanewindows/fixed.py
threepanewindows/py.typed
threepanewindows/themes.py
threepanewindows/utils/__init__.py
threepanewindows/utils/base.py
threepanewindows/utils/linux.py
threepanewindows/utils/macos.py
threepanewindows/utils/windows.py
threepanewindows-1.2.0.dist-info/licenses/LICENSE
threepanewindows-stubs/__init__.pyi
threepanewindows-stubs/_version.pyi
threepanewindows-stubs/cli.pyi
threepanewindows-stubs/custom_scrollbar.pyi
threepanewindows-stubs/dockable.pyi
threepanewindows-stubs/enhanced_dockable.pyi
threepanewindows-stubs/examples.pyi
threepanewindows-stubs/fixed.pyi
threepanewindows-stubs/py.typed
threepanewindows-stubs/setup.py
threepanewindows-stubs/themes.pyi
threepanewindows-stubs/utils/__init__.pyi
threepanewindows-stubs/utils/base.pyi
threepanewindows-stubs/utils/linux.pyi
threepanewindows-stubs/utils/macos.pyi
threepanewindows-stubs/utils/windows.pyi
threepanewindows-1.2.0.dist-info/METADATA
threepanewindows-1.2.0.dist-info/WHEEL
threepanewindows-1.2.0.dist-info/entry_points.txt
threepanewindows-1.2.0.dist-info/top_level.txt
threepanewindows-1.2.0.dist-info/RECORD
