Metadata-Version: 2.4
Name: threepanewindows
Version: 1.2.0
Summary: Professional three-pane window layouts for Tkinter applications with docking, theming, and advanced UI components
Home-page: https://github.com/stntg/threepanewindows
Author: Stan Griffiths
Author-email: Stan Griffiths <stantgriffiths@gmail.com>
Maintainer-email: Stan Griffiths <stantgriffiths@gmail.com>
License: MIT
Project-URL: Homepage, https://github.com/stntg/threepanewindows
Project-URL: Documentation, https://stntg.github.io/ThreePaneWindows/
Project-URL: Repository, https://github.com/stntg/threepanewindows.git
Project-URL: Bug Tracker, https://github.com/stntg/threepanewindows/issues
Project-URL: Changelog, https://github.com/stntg/threepanewindows/blob/main/CHANGELOG.md
Project-URL: Source Code, https://github.com/stntg/threepanewindows
Keywords: tkinter,gui,layout,three-pane,dockable,ui,desktop,application,framework
Classifier: Development Status :: 5 - Production/Stable
Classifier: Intended Audience :: Developers
Classifier: License :: OSI Approved :: MIT License
Classifier: Operating System :: OS Independent
Classifier: Programming Language :: Python :: 3
Classifier: Programming Language :: Python :: 3.9
Classifier: Programming Language :: Python :: 3.10
Classifier: Programming Language :: Python :: 3.11
Classifier: Programming Language :: Python :: 3.12
Classifier: Programming Language :: Python :: 3.13
Classifier: Topic :: Software Development :: Libraries :: Python Modules
Classifier: Topic :: Software Development :: User Interfaces
Classifier: Topic :: Desktop Environment
Classifier: Environment :: X11 Applications
Classifier: Environment :: Win32 (MS Windows)
Classifier: Environment :: MacOS X
Requires-Python: >=3.9
License-File: LICENSE
Requires-Dist: typing-extensions>=4.0.0; python_version < "3.10"
Provides-Extra: theme
Requires-Dist: darkdetect>=0.7.0; extra == "theme"
Provides-Extra: dev
Requires-Dist: pytest>=7.0; extra == "dev"
Requires-Dist: pytest-cov>=4.0; extra == "dev"
Requires-Dist: pytest-xvfb>=2.0; sys_platform == "linux" and extra == "dev"
Requires-Dist: pytest-timeout>=2.0; extra == "dev"
Requires-Dist: black>=22.0; extra == "dev"
Requires-Dist: flake8>=5.0; extra == "dev"
Requires-Dist: mypy>=1.0; extra == "dev"
Requires-Dist: isort>=5.0; extra == "dev"
Requires-Dist: pre-commit>=2.20; extra == "dev"
Requires-Dist: bandit>=1.7; extra == "dev"
Requires-Dist: safety>=2.0; extra == "dev"
Requires-Dist: tox>=4.0; extra == "dev"
Requires-Dist: darkdetect>=0.7.0; extra == "dev"
Provides-Extra: docs
Requires-Dist: sphinx>=5.0; extra == "docs"
Requires-Dist: sphinx-rtd-theme>=1.0; extra == "docs"
Requires-Dist: myst-parser>=0.18; extra == "docs"
Requires-Dist: sphinx-autodoc-typehints>=1.19; extra == "docs"
Requires-Dist: sphinx-copybutton>=0.5; extra == "docs"
Provides-Extra: test
Requires-Dist: pytest>=7.0; extra == "test"
Requires-Dist: pytest-cov>=4.0; extra == "test"
Requires-Dist: pytest-xvfb>=2.0; sys_platform == "linux" and extra == "test"
Requires-Dist: pytest-timeout>=2.0; extra == "test"
Requires-Dist: darkdetect>=0.7.0; extra == "test"
Dynamic: author
Dynamic: home-page
Dynamic: license-file
Dynamic: requires-python
